matchco/__init__.py
matchco/algorithms.py
matchco/matching.py
matchco/util.py
matchco-1.3.dist-info/LICENSE.txt
matchco-1.3.dist-info/METADATA
matchco-1.3.dist-info/WHEEL
matchco-1.3.dist-info/top_level.txt
matchco-1.3.dist-info/RECORD
